bode_logger/__init__.py
bode_logger/_bode_logger.py
bode_logger/gunicorn_logger/__init__.py
bode_logger/gunicorn_logger/_gunicorn_logger.py
bode_logger/structure_to_raw/__init__.py
bode_logger/structure_to_raw/_structure_to_raw.py
bode_logger-0.0.21.dist-info/METADATA
bode_logger-0.0.21.dist-info/WHEEL
bode_logger-0.0.21.dist-info/top_level.txt
bode_logger-0.0.21.dist-info/RECORD
