Metadata-Version: 2.4
Name: bode_logger
Version: 0.0.21
Summary: Logger for BODE framework
Requires-Dist: flask
Provides-Extra: gunicorn
Requires-Dist: gunicorn; extra == "gunicorn"
